{
    "projectId": "68d6d4060020e39899f6",
    "projectName": "Waha",
    "settings": {
        "services": {
            "account": true,
            "avatars": true,
            "databases": true,
            "locale": true,
            "health": true,
            "storage": true,
            "teams": true,
            "users": true,
            "sites": true,
            "functions": true,
            "graphql": true,
            "messaging": true
        },
        "auth": {
            "methods": {
                "jwt": true,
                "phone": true,
                "invites": true,
                "anonymous": true,
                "email-otp": true,
                "magic-url": true,
                "email-password": true
            },
            "security": {
                "duration": 31536000,
                "limit": 0,
                "sessionsLimit": 10,
                "passwordHistory": 0,
                "passwordDictionary": false,
                "personalDataCheck": false,
                "sessionAlerts": false,
                "mockNumbers": []
            }
        }
    },
    "functions": [
        {
            "$id": "68dabd3a000fe5ce4525",
            "execute": [
                "any",
                "users"
            ],
            "name": "ImportCsvFunction",
            "enabled": true,
            "logging": true,
            "runtime": "node-16.0",
            "scopes": [
                "databases.read",
                "databases.write",
                "documents.read",
                "documents.write",
                "files.read"
            ],
            "events": [
                "buckets.68d7cd3a0019edb5703b.files.*.create"
            ],
            "schedule": "",
            "timeout": 600,
            "entrypoint": "src/main.js",
            "commands": "npm install",
            "path": "functions/ImportCsvFunction",
            "specification": "s-1vcpu-512mb"
        },
        {
            "$id": "sendWhatsAppFunction",
            "execute": [
                "users"
            ],
            "name": "sendWhatsAppFunction",
            "enabled": true,
            "logging": true,
            "runtime": "node-16.0",
            "scopes": [
                "databases.read",
                "databases.write",
                "documents.read",
                "documents.write"
            ],
            "events": [],
            "schedule": "",
            "timeout": 300,
            "entrypoint": "src/main.js",
            "commands": "npm install",
            "path": "functions/sendWhatsAppFunction",
            "specification": "s-1vcpu-512mb"
        }
    ],
    "databases": [
        {
            "$id": "68d78cb20028fac621d4",
            "name": "Waha",
            "enabled": true
        }
    ],
    "collections": [
        {
            "$id": "templates",
            "$permissions": [
                "create(\"users\")",
                "read(\"users\")",
                "update(\"users\")",
                "delete(\"users\")"
            ],
            "databaseId": "68d78cb20028fac621d4",
            "name": "Plantillas",
            "enabled": true,
            "documentSecurity": false,
            "attributes": [
                {
                    "key": "name",
                    "type": "string",
                    "required": true,
                    "array": false,
                    "size": 255,
                    "encrypt": false,
                    "default": null
                },
                {
                    "key": "messages",
                    "type": "string",
                    "required": true,
                    "array": true,
                    "size": 10000,
                    "encrypt": false,
                    "default": null
                },
                {
                    "key": "imageUrls",
                    "type": "string",
                    "required": false,
                    "array": true,
                    "size": 2048,
                    "encrypt": false,
                    "default": null
                }
            ],
            "indexes": []
        },
        {
            "$id": "campaigns",
            "$permissions": [
                "create(\"users\")",
                "read(\"users\")",
                "update(\"users\")",
                "delete(\"users\")"
            ],
            "databaseId": "68d78cb20028fac621d4",
            "name": "Campanas",
            "enabled": true,
            "documentSecurity": false,
            "attributes": [
                {
                    "key": "status",
                    "type": "string",
                    "required": true,
                    "array": false,
                    "size": 50,
                    "encrypt": false,
                    "default": null
                },
                {
                    "key": "name",
                    "type": "string",
                    "required": true,
                    "array": false,
                    "size": 255,
                    "encrypt": false,
                    "default": null
                },
                {
                    "key": "templateId",
                    "type": "string",
                    "required": true,
                    "array": false,
                    "size": 255,
                    "encrypt": false,
                    "default": null
                },
                {
                    "key": "audienceCount",
                    "type": "integer",
                    "required": true,
                    "array": false,
                    "min": -9223372036854775808,
                    "max": 9223372036854775807,
                    "default": null
                },
                {
                    "key": "createdAt",
                    "type": "datetime",
                    "required": true,
                    "array": false,
                    "default": null
                },
                {
                    "key": "scheduledDate",
                    "type": "string",
                    "size": 50,
                    "required": false,
                    "array": false,
                    "encrypt": false,
                    "default": null
                },
                {
                    "key": "scheduledTime",
                    "type": "string",
                    "size": 10,
                    "required": false,
                    "array": false,
                    "encrypt": false,
                    "default": null
                },
                {
                    "key": "startTime",
                    "type": "string",
                    "size": 10,
                    "required": false,
                    "array": false,
                    "encrypt": false,
                    "default": null
                },
                {
                    "key": "endTime",
                    "type": "string",
                    "size": 10,
                    "required": false,
                    "array": false,
                    "encrypt": false,
                    "default": null
                },
                {
                    "key": "selectedMessageIndex",
                    "type": "integer",
                    "required": false,
                    "array": false,
                    "min": -9223372036854775808,
                    "max": 9223372036854775807,
                    "default": null
                },
                {
                    "key": "selectedImageIndex",
                    "type": "integer",
                    "required": false,
                    "array": false,
                    "min": -9223372036854775808,
                    "max": 9223372036854775807,
                    "default": null
                }
            ],
            "indexes": []
        },
        {
            "$id": "config",
            "$permissions": [
                "create(\"users\")",
                "read(\"users\")",
                "update(\"users\")",
                "delete(\"users\")"
            ],
            "databaseId": "68d78cb20028fac621d4",
            "name": "Configuracion",
            "enabled": true,
            "documentSecurity": false,
            "attributes": [
                {
                    "key": "apiUrl",
                    "type": "string",
                    "required": true,
                    "array": false,
                    "size": 255,
                    "encrypt": false,
                    "default": null
                },
                {
                    "key": "minDelayMs",
                    "type": "integer",
                    "required": false,
                    "array": false,
                    "min": -9223372036854775808,
                    "max": 9223372036854775807,
                    "default": null
                },
                {
                    "key": "maxDelayMs",
                    "type": "integer",
                    "required": false,
                    "array": false,
                    "min": -9223372036854775808,
                    "max": 9223372036854775807,
                    "default": null
                },
                {
                    "key": "batchSizeMin",
                    "type": "integer",
                    "required": false,
                    "array": false,
                    "min": -9223372036854775808,
                    "max": 9223372036854775807,
                    "default": null
                },
                {
                    "key": "batchSizeMax",
                    "type": "integer",
                    "required": false,
                    "array": false,
                    "min": -9223372036854775808,
                    "max": 9223372036854775807,
                    "default": null
                },
                {
                    "key": "batchDelayMsMin",
                    "type": "integer",
                    "required": false,
                    "array": false,
                    "min": -9223372036854775808,
                    "max": 9223372036854775807,
                    "default": null
                },
                {
                    "key": "batchDelayMsMax",
                    "type": "integer",
                    "required": false,
                    "array": false,
                    "min": -9223372036854775808,
                    "max": 9223372036854775807,
                    "default": null
                },
                {
                    "key": "adminPhoneNumbers",
                    "type": "string",
                    "required": false,
                    "array": true,
                    "size": 30,
                    "encrypt": false,
                    "default": null
                },
                {
                    "key": "notificationInterval",
                    "type": "integer",
                    "required": false,
                    "array": false,
                    "min": -9223372036854775808,
                    "max": 9223372036854775807,
                    "default": null
                }
            ],
            "indexes": []
        },
        {
            "$id": "clients",
            "$permissions": [
                "create(\"users\")",
                "read(\"users\")",
                "update(\"users\")",
                "delete(\"users\")",
                "create(\"any\")",
                "read(\"any\")",
                "update(\"any\")",
                "delete(\"any\")"
            ],
            "databaseId": "68d78cb20028fac621d4",
            "name": "Clientes_Import",
            "enabled": true,
            "documentSecurity": false,
            "attributes": [
                {
                    "key": "codcli",
                    "type": "string",
                    "required": true,
                    "array": false,
                    "size": 50,
                    "encrypt": false,
                    "default": null
                },
                {
                    "key": "nomcli",
                    "type": "string",
                    "required": false,
                    "array": false,
                    "size": 100,
                    "encrypt": false,
                    "default": null
                },
                {
                    "key": "ape1cli",
                    "type": "string",
                    "required": false,
                    "array": false,
                    "size": 200,
                    "encrypt": false,
                    "default": null
                },
                {
                    "key": "nombre_completo",
                    "type": "string",
                    "required": false,
                    "array": false,
                    "size": 512,
                    "encrypt": false,
                    "default": null
                },
                {
                    "key": "dnicli",
                    "type": "string",
                    "required": false,
                    "array": false,
                    "size": 20,
                    "encrypt": false,
                    "default": null
                },
                {
                    "key": "email",
                    "type": "string",
                    "required": false,
                    "array": false,
                    "size": 255,
                    "encrypt": false,
                    "default": null
                },
                {
                    "key": "dircli",
                    "type": "string",
                    "required": false,
                    "array": false,
                    "size": 255,
                    "encrypt": false,
                    "default": null
                },
                {
                    "key": "codposcli",
                    "type": "string",
                    "required": false,
                    "array": false,
                    "size": 10,
                    "encrypt": false,
                    "default": null
                },
                {
                    "key": "pobcli",
                    "type": "string",
                    "required": false,
                    "array": false,
                    "size": 100,
                    "encrypt": false,
                    "default": null
                },
                {
                    "key": "procli",
                    "type": "string",
                    "required": false,
                    "array": false,
                    "size": 100,
                    "encrypt": false,
                    "default": null
                },
                {
                    "key": "tel1cli",
                    "type": "string",
                    "required": false,
                    "array": false,
                    "size": 20,
                    "encrypt": false,
                    "default": null
                },
                {
                    "key": "tel2cli",
                    "type": "string",
                    "required": false,
                    "array": false,
                    "size": 20,
                    "encrypt": false,
                    "default": null
                },
                {
                    "key": "fecnac",
                    "type": "datetime",
                    "required": false,
                    "array": false,
                    "default": null
                },
                {
                    "key": "fecalta",
                    "type": "datetime",
                    "required": false,
                    "array": false,
                    "default": null
                },
                {
                    "key": "sexo",
                    "type": "string",
                    "required": false,
                    "array": false,
                    "size": 10,
                    "encrypt": false,
                    "default": null,
                    "format": "enum",
                    "elements": [
                        "M",
                        "H",
                        "Otro"
                    ]
                },
                {
                    "key": "edad",
                    "type": "integer",
                    "required": false,
                    "array": false,
                    "min": -9223372036854775808,
                    "max": 9223372036854775807,
                    "default": null
                },
                {
                    "key": "enviar",
                    "type": "integer",
                    "required": false,
                    "array": false,
                    "min": -9223372036854775808,
                    "max": 9223372036854775807,
                    "default": 1
                },
                {
                    "key": "importErrors",
                    "type": "string",
                    "required": false,
                    "array": true,
                    "size": 2000,
                    "encrypt": false,
                    "default": null
                },
                {
                    "key": "facturacion",
                    "type": "double",
                    "required": false,
                    "array": false,
                    "min": -1.7976931348623157e+308,
                    "max": 1.7976931348623157e+308,
                    "default": null
                },
                {
                    "key": "intereses",
                    "type": "string",
                    "required": false,
                    "array": true,
                    "size": 255,
                    "encrypt": false,
                    "default": null
                }
            ],
            "indexes": [
                {
                    "key": "search_nombre_completo",
                    "type": "fulltext",
                    "attributes": [
                        "nombre_completo"
                    ],
                    "orders": [
                        "ASC"
                    ]
                },
                {
                    "key": "nomcliFullText",
                    "type": "fulltext",
                    "attributes": [
                        "nomcli"
                    ],
                    "orders": [
                        "ASC"
                    ]
                },
                {
                    "key": "ape1cliFullText",
                    "type": "fulltext",
                    "attributes": [
                        "ape1cli"
                    ],
                    "orders": [
                        "ASC"
                    ]
                },
                {
                    "key": "emailFullText",
                    "type": "fulltext",
                    "attributes": [
                        "email"
                    ],
                    "orders": [
                        "ASC"
                    ]
                },
                {
                    "key": "provFT",
                    "type": "fulltext",
                    "attributes": [
                        "procli"
                    ],
                    "orders": [
                        "ASC"
                    ]
                },
                {
                    "key": "pobFT",
                    "type": "fulltext",
                    "attributes": [
                        "pobcli"
                    ],
                    "orders": [
                        "ASC"
                    ]
                },
                {
                    "key": "codigoFT",
                    "type": "fulltext",
                    "attributes": [
                        "codcli"
                    ],
                    "orders": [
                        "ASC"
                    ]
                },
                {
                    "key": "dniFT",
                    "type": "fulltext",
                    "attributes": [
                        "dnicli"
                    ],
                    "orders": [
                        "ASC"
                    ]
                },
                {
                    "key": "dirFT",
                    "type": "fulltext",
                    "attributes": [
                        "dircli"
                    ],
                    "orders": [
                        "ASC"
                    ]
                },
                {
                    "key": "cpFT",
                    "type": "fulltext",
                    "attributes": [
                        "codposcli"
                    ],
                    "orders": [
                        "ASC"
                    ]
                },
                {
                    "key": "tfnoFT",
                    "type": "fulltext",
                    "attributes": [
                        "tel2cli"
                    ],
                    "orders": [
                        "ASC"
                    ]
                }
            ]
        },
        {
            "$id": "IMPORT_LOGS_COLLECTION_ID",
            "$permissions": [
                "read(\"users\")",
                "create(\"users\")",
                "update(\"users\")",
                "delete(\"users\")",
                "create(\"any\")",
                "read(\"any\")",
                "update(\"any\")",
                "delete(\"any\")"
            ],
            "databaseId": "68d78cb20028fac621d4",
            "name": "import_logs",
            "enabled": true,
            "documentSecurity": true,
            "attributes": [
                {
                    "key": "timestamp",
                    "type": "datetime",
                    "required": true,
                    "array": false,
                    "default": null
                },
                {
                    "key": "filename",
                    "type": "string",
                    "required": true,
                    "array": false,
                    "size": 255,
                    "encrypt": false,
                    "default": null
                },
                {
                    "key": "successfulImports",
                    "type": "integer",
                    "required": true,
                    "array": false,
                    "min": -9223372036854775808,
                    "max": 9223372036854775807,
                    "default": null
                },
                {
                    "key": "totalProcessed",
                    "type": "integer",
                    "required": true,
                    "array": false,
                    "min": -9223372036854775808,
                    "max": 9223372036854775807,
                    "default": null
                },
                {
                    "key": "errors",
                    "type": "string",
                    "required": false,
                    "array": true,
                    "size": 2000,
                    "encrypt": false,
                    "default": null
                },
                {
                    "key": "status",
                    "type": "string",
                    "required": true,
                    "array": false,
                    "size": 50,
                    "encrypt": false,
                    "default": null
                }
            ],
            "indexes": []
        },
        {
            "$id": "message_logs",
            "$permissions": [
                "create(\"users\")",
                "read(\"users\")"
            ],
            "databaseId": "68d78cb20028fac621d4",
            "name": "MessageLogs",
            "enabled": true,
            "documentSecurity": false,
            "attributes": [
                {
                    "key": "campaignId",
                    "type": "string",
                    "required": true,
                    "array": false,
                    "size": 255,
                    "encrypt": false,
                    "default": null
                },
                {
                    "key": "clientId",
                    "type": "string",
                    "required": true,
                    "array": false,
                    "size": 255,
                    "encrypt": false,
                    "default": null
                },
                {
                    "key": "status",
                    "type": "string",
                    "required": true,
                    "array": false,
                    "size": 50,
                    "encrypt": false,
                    "default": null
                },
                {
                    "key": "timestamp",
                    "type": "datetime",
                    "required": true,
                    "array": false,
                    "default": null
                },
                {
                    "key": "error",
                    "type": "string",
                    "required": false,
                    "array": false,
                    "size": 500,
                    "encrypt": false,
                    "default": null
                }
            ],
            "indexes": [
                {
                    "key": "campaingId_index",
                    "type": "key",
                    "attributes": [
                        "campaignId"
                    ],
                    "orders": [
                        "ASC"
                    ]
                }
            ]
        }
    ],
    "buckets": [
        {
            "$id": "68d7cd3a0019edb5703b",
            "$permissions": [
                "create(\"users\")",
                "read(\"users\")",
                "update(\"users\")",
                "delete(\"users\")"
            ],
            "fileSecurity": true,
            "name": "Import",
            "enabled": true,
            "maximumFileSize": 30000000,
            "allowedFileExtensions": [],
            "compression": "none",
            "encryption": true,
            "antivirus": true
        }
    ],
    "tablesDB": [
        {
            "$id": "68d78cb20028fac621d4",
            "name": "Waha",
            "enabled": true
        }
    ],
    "tables": [
        {
            "$id": "config",
            "$permissions": [
                "create(\"users\")",
                "read(\"users\")",
                "update(\"users\")",
                "delete(\"users\")"
            ],
            "databaseId": "68d78cb20028fac621d4",
            "name": "Configuracion",
            "enabled": true,
            "rowSecurity": false,
            "columns": [
                {
                    "key": "apiUrl",
                    "type": "string",
                    "required": true,
                    "array": false,
                    "size": 255,
                    "default": null,
                    "encrypt": false
                },
                {
                    "key": "minDelayMs",
                    "type": "integer",
                    "required": false,
                    "array": false,
                    "min": -9223372036854775808,
                    "max": 9223372036854775807,
                    "default": null
                },
                {
                    "key": "maxDelayMs",
                    "type": "integer",
                    "required": false,
                    "array": false,
                    "min": -9223372036854775808,
                    "max": 9223372036854775807,
                    "default": null
                },
                {
                    "key": "batchSizeMin",
                    "type": "integer",
                    "required": false,
                    "array": false,
                    "min": -9223372036854775808,
                    "max": 9223372036854775807,
                    "default": null
                },
                {
                    "key": "batchSizeMax",
                    "type": "integer",
                    "required": false,
                    "array": false,
                    "min": -9223372036854775808,
                    "max": 9223372036854775807,
                    "default": null
                },
                {
                    "key": "batchDelayMsMin",
                    "type": "integer",
                    "required": false,
                    "array": false,
                    "min": -9223372036854775808,
                    "max": 9223372036854775807,
                    "default": null
                },
                {
                    "key": "batchDelayMsMax",
                    "type": "integer",
                    "required": false,
                    "array": false,
                    "min": -9223372036854775808,
                    "max": 9223372036854775807,
                    "default": null
                },
                {
                    "key": "notificationInterval",
                    "type": "integer",
                    "required": false,
                    "array": false,
                    "min": -9223372036854775808,
                    "max": 9223372036854775807,
                    "default": null
                },
                {
                    "key": "adminPhoneNumbers",
                    "type": "string",
                    "required": false,
                    "array": true,
                    "size": 30,
                    "default": null,
                    "encrypt": false
                }
            ],
            "indexes": []
        },
        {
            "$id": "clients",
            "$permissions": [
                "create(\"users\")",
                "read(\"users\")",
                "update(\"users\")",
                "delete(\"users\")",
                "create(\"any\")",
                "read(\"any\")",
                "update(\"any\")",
                "delete(\"any\")"
            ],
            "databaseId": "68d78cb20028fac621d4",
            "name": "Clientes_Import",
            "enabled": true,
            "rowSecurity": false,
            "columns": [
                {
                    "key": "codcli",
                    "type": "string",
                    "required": true,
                    "array": false,
                    "size": 50,
                    "default": null,
                    "encrypt": false
                },
                {
                    "key": "nomcli",
                    "type": "string",
                    "required": false,
                    "array": false,
                    "size": 100,
                    "default": null,
                    "encrypt": false
                },
                {
                    "key": "ape1cli",
                    "type": "string",
                    "required": false,
                    "array": false,
                    "size": 200,
                    "default": null,
                    "encrypt": false
                },
                {
                    "key": "dnicli",
                    "type": "string",
                    "required": false,
                    "array": false,
                    "size": 20,
                    "default": null,
                    "encrypt": false
                },
                {
                    "key": "email",
                    "type": "string",
                    "required": false,
                    "array": false,
                    "size": 255,
                    "default": null,
                    "encrypt": false
                },
                {
                    "key": "dircli",
                    "type": "string",
                    "required": false,
                    "array": false,
                    "size": 255,
                    "default": null,
                    "encrypt": false
                },
                {
                    "key": "codposcli",
                    "type": "string",
                    "required": false,
                    "array": false,
                    "size": 10,
                    "default": null,
                    "encrypt": false
                },
                {
                    "key": "pobcli",
                    "type": "string",
                    "required": false,
                    "array": false,
                    "size": 100,
                    "default": null,
                    "encrypt": false
                },
                {
                    "key": "procli",
                    "type": "string",
                    "required": false,
                    "array": false,
                    "size": 100,
                    "default": null,
                    "encrypt": false
                },
                {
                    "key": "tel1cli",
                    "type": "string",
                    "required": false,
                    "array": false,
                    "size": 20,
                    "default": null,
                    "encrypt": false
                },
                {
                    "key": "tel2cli",
                    "type": "string",
                    "required": false,
                    "array": false,
                    "size": 20,
                    "default": null,
                    "encrypt": false
                },
                {
                    "key": "fecnac",
                    "type": "datetime",
                    "required": false,
                    "array": false,
                    "format": "",
                    "default": null
                },
                {
                    "key": "fecalta",
                    "type": "datetime",
                    "required": false,
                    "array": false,
                    "format": "",
                    "default": null
                },
                {
                    "key": "sexo",
                    "type": "string",
                    "required": false,
                    "array": false,
                    "elements": [
                        "M",
                        "H",
                        "Otro"
                    ],
                    "format": "enum",
                    "default": null
                },
                {
                    "key": "edad",
                    "type": "integer",
                    "required": false,
                    "array": false,
                    "min": -9223372036854775808,
                    "max": 9223372036854775807,
                    "default": null
                },
                {
                    "key": "enviar",
                    "type": "integer",
                    "required": false,
                    "array": false,
                    "min": -9223372036854775808,
                    "max": 9223372036854775807,
                    "default": 1
                },
                {
                    "key": "importErrors",
                    "type": "string",
                    "required": false,
                    "array": true,
                    "size": 2000,
                    "default": null,
                    "encrypt": false
                },
                {
                    "key": "intereses",
                    "type": "string",
                    "required": false,
                    "array": true,
                    "size": 255,
                    "default": null,
                    "encrypt": false
                },
                {
                    "key": "nombre_completo",
                    "type": "string",
                    "required": true,
                    "array": false,
                    "size": 600,
                    "default": null,
                    "encrypt": false
                },
                {
                    "key": "facturacion",
                    "type": "double",
                    "required": false,
                    "array": false,
                    "min": 1000000,
                    "max": 100000000,
                    "default": null
                }
            ],
            "indexes": [
                {
                    "key": "nombre_completo",
                    "type": "fulltext",
                    "status": "available",
                    "columns": [
                        "nombre_completo"
                    ],
                    "orders": [
                        "ASC"
                    ]
                },
                {
                    "key": "codcli",
                    "type": "fulltext",
                    "status": "available",
                    "columns": [
                        "codcli"
                    ],
                    "orders": [
                        "ASC"
                    ]
                },
                {
                    "key": "nomcli",
                    "type": "fulltext",
                    "status": "available",
                    "columns": [
                        "nomcli"
                    ],
                    "orders": [
                        "ASC"
                    ]
                },
                {
                    "key": "dnicli",
                    "type": "fulltext",
                    "status": "available",
                    "columns": [
                        "dnicli"
                    ],
                    "orders": [
                        "ASC"
                    ]
                },
                {
                    "key": "email",
                    "type": "fulltext",
                    "status": "available",
                    "columns": [
                        "email"
                    ],
                    "orders": [
                        "ASC"
                    ]
                },
                {
                    "key": "dircli",
                    "type": "fulltext",
                    "status": "available",
                    "columns": [
                        "dircli"
                    ],
                    "orders": [
                        "ASC"
                    ]
                },
                {
                    "key": "codposcli",
                    "type": "fulltext",
                    "status": "available",
                    "columns": [
                        "codposcli"
                    ],
                    "orders": [
                        "ASC"
                    ]
                },
                {
                    "key": "pobcli",
                    "type": "fulltext",
                    "status": "available",
                    "columns": [
                        "pobcli"
                    ],
                    "orders": [
                        "ASC"
                    ]
                },
                {
                    "key": "procli",
                    "type": "fulltext",
                    "status": "available",
                    "columns": [
                        "procli"
                    ],
                    "orders": [
                        "ASC"
                    ]
                },
                {
                    "key": "tel2cli",
                    "type": "fulltext",
                    "status": "available",
                    "columns": [
                        "tel2cli"
                    ],
                    "orders": [
                        "ASC"
                    ]
                },
                {
                    "key": "fecnac",
                    "type": "key",
                    "status": "available",
                    "columns": [
                        "fecnac"
                    ],
                    "orders": [
                        "ASC"
                    ]
                }
            ]
        },
        {
            "$id": "IMPORT_LOGS_COLLECTION_ID",
            "$permissions": [
                "create(\"users\")",
                "read(\"users\")",
                "update(\"users\")",
                "delete(\"users\")",
                "create(\"any\")",
                "read(\"any\")",
                "update(\"any\")",
                "delete(\"any\")"
            ],
            "databaseId": "68d78cb20028fac621d4",
            "name": "import_logs",
            "enabled": true,
            "rowSecurity": false,
            "columns": [
                {
                    "key": "timestamp",
                    "type": "datetime",
                    "required": true,
                    "array": false,
                    "format": "",
                    "default": null
                },
                {
                    "key": "filename",
                    "type": "string",
                    "required": true,
                    "array": false,
                    "size": 255,
                    "default": null,
                    "encrypt": false
                },
                {
                    "key": "successfulImports",
                    "type": "integer",
                    "required": true,
                    "array": false,
                    "min": -9223372036854775808,
                    "max": 9223372036854775807,
                    "default": null
                },
                {
                    "key": "totalProcessed",
                    "type": "integer",
                    "required": true,
                    "array": false,
                    "min": -9223372036854775808,
                    "max": 9223372036854775807,
                    "default": null
                },
                {
                    "key": "errors",
                    "type": "string",
                    "required": false,
                    "array": true,
                    "size": 2000,
                    "default": null,
                    "encrypt": false
                },
                {
                    "key": "status",
                    "type": "string",
                    "required": true,
                    "array": false,
                    "size": 50,
                    "default": null,
                    "encrypt": false
                }
            ],
            "indexes": []
        },
        {
            "$id": "message_logs",
            "$permissions": [
                "create(\"users\")",
                "read(\"users\")"
            ],
            "databaseId": "68d78cb20028fac621d4",
            "name": "MessageLogs",
            "enabled": true,
            "rowSecurity": false,
            "columns": [
                {
                    "key": "campaignId",
                    "type": "string",
                    "required": true,
                    "array": false,
                    "size": 255,
                    "default": null,
                    "encrypt": false
                },
                {
                    "key": "clientId",
                    "type": "string",
                    "required": true,
                    "array": false,
                    "size": 255,
                    "default": null,
                    "encrypt": false
                },
                {
                    "key": "status",
                    "type": "string",
                    "required": true,
                    "array": false,
                    "size": 50,
                    "default": null,
                    "encrypt": false
                },
                {
                    "key": "timestamp",
                    "type": "datetime",
                    "required": true,
                    "array": false,
                    "format": "",
                    "default": null
                },
                {
                    "key": "error",
                    "type": "string",
                    "required": false,
                    "array": false,
                    "size": 500,
                    "default": null,
                    "encrypt": false
                }
            ],
            "indexes": [
                {
                    "key": "campaingId_index",
                    "type": "key",
                    "status": "available",
                    "columns": [
                        "campaignId"
                    ],
                    "orders": [
                        "ASC"
                    ]
                }
            ]
        },
        {
            "$id": "templates",
            "$permissions": [
                "create(\"users\")",
                "read(\"users\")",
                "update(\"users\")",
                "delete(\"users\")"
            ],
            "databaseId": "68d78cb20028fac621d4",
            "name": "Plantillas",
            "enabled": true,
            "rowSecurity": false,
            "columns": [
                {
                    "key": "name",
                    "type": "string",
                    "required": true,
                    "array": false,
                    "size": 255,
                    "default": null,
                    "encrypt": false
                },
                {
                    "key": "messages",
                    "type": "string",
                    "required": true,
                    "array": true,
                    "size": 10000,
                    "default": null,
                    "encrypt": false
                },
                {
                    "key": "imageUrls",
                    "type": "string",
                    "required": false,
                    "array": true,
                    "size": 2048,
                    "default": null,
                    "encrypt": false
                }
            ],
            "indexes": []
        },
        {
            "$id": "campaigns",
            "$permissions": [
                "create(\"users\")",
                "read(\"users\")",
                "update(\"users\")",
                "delete(\"users\")"
            ],
            "databaseId": "68d78cb20028fac621d4",
            "name": "Campanas",
            "enabled": true,
            "rowSecurity": false,
            "columns": [
                {
                    "key": "name",
                    "type": "string",
                    "required": true,
                    "array": false,
                    "size": 255,
                    "default": null,
                    "encrypt": false
                },
                {
                    "key": "templateId",
                    "type": "string",
                    "required": true,
                    "array": false,
                    "size": 255,
                    "default": null,
                    "encrypt": false
                },
                {
                    "key": "status",
                    "type": "string",
                    "required": true,
                    "array": false,
                    "size": 50,
                    "default": null,
                    "encrypt": false
                },
                {
                    "key": "audienceCount",
                    "type": "integer",
                    "required": true,
                    "array": false,
                    "min": -9223372036854775808,
                    "max": 9223372036854775807,
                    "default": null
                },
                {
                    "key": "createdAt",
                    "type": "datetime",
                    "required": true,
                    "array": false,
                    "format": "",
                    "default": null
                },
                {
                    "key": "scheduledDate",
                    "type": "string",
                    "required": false,
                    "array": false,
                    "size": 50,
                    "default": null,
                    "encrypt": false
                },
                {
                    "key": "scheduledTime",
                    "type": "string",
                    "required": false,
                    "array": false,
                    "size": 10,
                    "default": null,
                    "encrypt": false
                },
                {
                    "key": "startTime",
                    "type": "string",
                    "required": false,
                    "array": false,
                    "size": 10,
                    "default": null,
                    "encrypt": false
                },
                {
                    "key": "endTime",
                    "type": "string",
                    "required": false,
                    "array": false,
                    "size": 10,
                    "default": null,
                    "encrypt": false
                },
                {
                    "key": "selectedMessageIndex",
                    "type": "integer",
                    "required": false,
                    "array": false,
                    "min": -9223372036854775808,
                    "max": 9223372036854775807,
                    "default": null
                },
                {
                    "key": "selectedImageIndex",
                    "type": "integer",
                    "required": false,
                    "array": false,
                    "min": -9223372036854775808,
                    "max": 9223372036854775807,
                    "default": null
                }
            ],
            "indexes": []
        }
    ]
}